asyml_utilities/__init__.py
asyml_utilities/hyperparams.py
asyml_utilities/special_tokens.py
asyml_utilities-0.0.2.dist-info/LICENSE
asyml_utilities-0.0.2.dist-info/METADATA
asyml_utilities-0.0.2.dist-info/WHEEL
asyml_utilities-0.0.2.dist-info/top_level.txt
asyml_utilities-0.0.2.dist-info/RECORD
