Metadata-Version: 2.1
Name: asyml-utilities
Version: 0.0.2
Summary: Shared Utilities for ASYML Projects
Home-page: https://github.com/asyml/asyml-utilities
License: Apache License Version 2.0
Platform: any
Classifier: Intended Audience :: Developers
Classifier: Intended Audience :: Education
Classifier: Intended Audience :: Science/Research
Classifier: Operating System :: OS Independent
Classifier: Programming Language :: Python
Classifier: Programming Language :: Python :: 3.6
Classifier: Programming Language :: Python :: 3.7
License-File: LICENSE
